younameit/__init__.py
younameit/__main__.py
younameit/__version__.py
younameit/_antirandom.py
younameit/_base.py
younameit/_hashing_function.py
younameit/_nomenclator.py
younameit/regenrate_cipher_book.py
younameit/books/american-english-book.yaml
younameit/books/british-english-book.yaml
younameit/books/finnish-book.yaml
younameit/books/french-book.yaml
younameit/books/german-book.yaml
younameit/books/italian-book.yaml
younameit/books/spanish-book.yaml
younameit-0.1.2.dist-info/LICENSE
younameit-0.1.2.dist-info/METADATA
younameit-0.1.2.dist-info/WHEEL
younameit-0.1.2.dist-info/entry_points.txt
younameit-0.1.2.dist-info/top_level.txt
younameit-0.1.2.dist-info/RECORD
